deteksi_gempa/__init__.py
latestearthquakeID-0.3.1.dist-info/LICENSE
latestearthquakeID-0.3.1.dist-info/METADATA
latestearthquakeID-0.3.1.dist-info/WHEEL
latestearthquakeID-0.3.1.dist-info/top_level.txt
latestearthquakeID-0.3.1.dist-info/RECORD
