Metadata-Version: 2.1
Name: latestearthquakeID
Version: 0.3.1
Summary: this package will get the latest earthquake from BMKG | Meteorological, Climatological, and Geophysical Agency
Home-page: https://github.com/Candyy1st/latest-indonesia-earthquake
Author: Dinda Wahyu Candradewa
Author-email: candradewa1981@gmail.com
License: UNKNOWN
Project-URL: Bug Tracker, https://github.com/Candyy1st/latest-indonesia-earthquake/issues
Platform: UNKNOWN
Classifier: Programming Language :: Python :: 3
Classifier: License :: OSI Approved :: GNU General Public License v3 (GPLv3)
Classifier: Operating System :: OS Independent
Classifier: Development Status :: 5 - Production/Stable
Requires-Python: >=3.6
License-File: LICENSE
